odoo/addons/website_sale_stock_provisioning_date/README.rst
odoo/addons/website_sale_stock_provisioning_date/__init__.py
odoo/addons/website_sale_stock_provisioning_date/__manifest__.py
odoo/addons/website_sale_stock_provisioning_date/i18n/es.po
odoo/addons/website_sale_stock_provisioning_date/i18n/it.po
odoo/addons/website_sale_stock_provisioning_date/i18n/website_sale_stock_provisioning_date.pot
odoo/addons/website_sale_stock_provisioning_date/models/__init__.py
odoo/addons/website_sale_stock_provisioning_date/models/product_product.py
odoo/addons/website_sale_stock_provisioning_date/models/product_template.py
odoo/addons/website_sale_stock_provisioning_date/readme/CONTRIBUTORS.rst
odoo/addons/website_sale_stock_provisioning_date/readme/DESCRIPTION.rst
odoo/addons/website_sale_stock_provisioning_date/readme/USAGE.rst
odoo/addons/website_sale_stock_provisioning_date/static/description/icon.png
odoo/addons/website_sale_stock_provisioning_date/static/description/index.html
odoo/addons/website_sale_stock_provisioning_date/static/src/js/website_sale_stock_provisioning_date.js
odoo/addons/website_sale_stock_provisioning_date/static/src/js/website_sale_stock_provisioning_date_tour.js
odoo/addons/website_sale_stock_provisioning_date/static/src/xml/website_sale_stock_product_availability.xml
odoo/addons/website_sale_stock_provisioning_date/tests/__init__.py
odoo/addons/website_sale_stock_provisioning_date/tests/test_website_sale_stock_provisioning_date.py
odoo/addons/website_sale_stock_provisioning_date/views/assets.xml
odoo/addons/website_sale_stock_provisioning_date/views/product_template_views.xml
odoo14_addon_website_sale_stock_provisioning_date-14.0.1.0.1.dev9.dist-info/METADATA
odoo14_addon_website_sale_stock_provisioning_date-14.0.1.0.1.dev9.dist-info/WHEEL
odoo14_addon_website_sale_stock_provisioning_date-14.0.1.0.1.dev9.dist-info/top_level.txt
odoo14_addon_website_sale_stock_provisioning_date-14.0.1.0.1.dev9.dist-info/RECORD
